CHANGELOG.txt
LICENCE.txt
MANIFEST.in
README.txt
setup.py
UNA_Support/CustomException.py
UNA_Support/Mail.py
UNA_Support/Utility.py
UNA_Support/__init__.py
UNA_Support/config_util.py
UNA_Support/getLog.py
UNA_Support.egg-info/PKG-INFO
UNA_Support.egg-info/SOURCES.txt
UNA_Support.egg-info/dependency_links.txt
UNA_Support.egg-info/top_level.txt
test/__init__.py