Metadata-Version: 1.1
Name: UNA-Support
Version: 0.0.6
Summary: UNA support modules
Home-page: UNKNOWN
Author: Gaidarji Nicolae
Author-email: nicolaegaidarji@gmail.com
License: MIT
Keywords: UNA
Platform: UNKNOWN
Classifier: Development Status :: 5 - Production/Stable
Classifier: Intended Audience :: Education
Classifier: Operating System :: Microsoft :: Windows :: Windows 10
Classifier: License :: OSI Approved :: MIT License
Classifier: Programming Language :: Python :: 2.7
